ark_rcon/__init__.py
ark_rcon/client.py
ark_rcon/common.py
ark_rcon/exceptions.py
ark_rcon/proto.py
ark_rcon/datastructures/__init__.py
ark_rcon/datastructures/logline.py
ark_rcon/datastructures/players.py
ark_rcon-0.0.4.dist-info/LICENSE
ark_rcon-0.0.4.dist-info/METADATA
ark_rcon-0.0.4.dist-info/WHEEL
ark_rcon-0.0.4.dist-info/top_level.txt
ark_rcon-0.0.4.dist-info/RECORD
